[
    {
        "channelNum": 1,
        "channelName": "安徽卫视",
        "channelUrl": "https://live1.ahtv.cn/ahws/playlist.m3u8?_upt=6a3240011762416617",
        "channelLogo": "https://gh-proxy.com/https://raw.githubusercontent.com/fanmingming/live/main/tv/安徽卫视.png"
    },
    {
        "channelNum": 2,
        "channelName": "北京卫视",
        "channelUrl": "https://hsplay-360.v.btime.com/live_btime/btv_sn_20170706_s1/index.m3u8?time=1762409407&sign=84a64f1559eaf589a5c0f775007df48c",
        "channelLogo": "https://gh-proxy.com/https://raw.githubusercontent.com/fanmingming/live/main/tv/北京卫视.png"
    },
    {
        "channelNum": 3,
        "channelName": "广西卫视",
        "channelUrl": "https://hlscdn.liangtv.cn/live/0c4ef3a44b934cacb8b47121dfada66c/d7e04258157b480dae53883cc6f8123b.m3u8",
        "channelLogo": "https://gh-proxy.com/https://raw.githubusercontent.com/fanmingming/live/main/tv/广西卫视.png"
    },
    {
        "channelNum": 4,
        "channelName": "贵州卫视",
        "channelUrl": "https://9bwaz8y2.gzstv.com/live/CH01_lo.m3u8?txSecret=f9c6ff6422e84a54fc48fee7f144bd48&txTime=690C34C4",
        "channelLogo": "https://gh-proxy.com/https://raw.githubusercontent.com/fanmingming/live/main/tv/贵州卫视.png"
    },
    {
        "channelNum": 5,
        "channelName": "海南卫视",
        "channelUrl": "https://livelyws.chinamcache.com/lyws/zb03.m3u8",
        "channelLogo": "https://gh-proxy.com/https://raw.githubusercontent.com/fanmingming/live/main/tv/海南卫视.png"
    },
    {
        "channelNum": 6,
        "channelName": "河北卫视",
        "channelUrl": "https://tv.pull.hebtv.com/jishi/weishipindao.m3u8?t=1762416620&k=1dbd496f6d16a6fb896ec759f9e2150c",
        "channelLogo": "https://gh-proxy.com/https://raw.githubusercontent.com/fanmingming/live/main/tv/河北卫视.png"
    },
    {
        "channelNum": 7,
        "channelName": "黑龙江卫视",
        "channelUrl": "https://idclive.hljtv.com:4430/live/hljws_own.m3u8",
        "channelLogo": "https://gh-proxy.com/https://raw.githubusercontent.com/fanmingming/live/main/tv/黑龙江卫视.png"
    },
    {
        "channelNum": 8,
        "channelName": "河南卫视",
        "channelUrl": "http://tvcdn.stream3.hndt.com/tv/65c4a6d5017e1000b2b6ea2500000000_transios/playlist.m3u8?wsSecret=e5cef8e9d95c352c74e355c3c2d27b24&wsTime=1762423806&wsSession=47787d6eb0f95f7dabcb335f-176240940630191&wsIPSercert=965199407363e75c3ccb566d6f002965&wsiphost=local&wsBindIP=1",
        "channelLogo": "https://gh-proxy.com/https://raw.githubusercontent.com/fanmingming/live/main/tv/河南卫视.png"
    },
    {
        "channelNum": 9,
        "channelName": "吉林卫视",
        "channelUrl": "https://hls.avap.jilintv.cn/zqvk7vpj/channel/0533b55e42354f4f802bdec78e26b571/index.m3u8?txSecret=e059d17d9eb79c4cf502554f689587f2&txTime=690C7496",
        "channelLogo": "https://gh-proxy.com/https://raw.githubusercontent.com/fanmingming/live/main/tv/吉林卫视.png"
    },
    {
        "channelNum": 10,
        "channelName": "内蒙古卫视",
        "channelUrl": "https://livestream-bt.nmtv.cn/nmtv/3208526general.m3u8?txSecret=eb5a3102dd5406c7ffeddf560b024952&txTime=76B2F9A0&token=2fa9c16d839a4b31a5e4abd6c8897013",
        "channelLogo": "https://gh-proxy.com/https://raw.githubusercontent.com/fanmingming/live/main/tv/内蒙古卫视.png"
    },
    {
        "channelNum": 11,
        "channelName": "山西卫视",
        "channelUrl": "https://livehhhttps.sxrtv.com/lsdream/q8RVWgs/1000/53sqsR0.m3u8",
        "channelLogo": "https://gh-proxy.com/https://raw.githubusercontent.com/fanmingming/live/main/tv/山西卫视.png"
    },
    {
        "channelNum": 12,
        "channelName": "陕西卫视",
        "channelUrl": "http://stream.snrtv.com/sxbc-star-blrKQ3.m3u8",
        "channelLogo": "https://gh-proxy.com/https://raw.githubusercontent.com/fanmingming/live/main/tv/陕西卫视.png"
    },
    {
        "channelNum": 13,
        "channelName": "西藏卫视",
        "channelUrl": "https://tv.vtibet.cn/live/h701F9MpxzPDyE.m3u8?secret=b698be1b2aef25cc5ace7eb00c5c8e47&time=690c3bbc",
        "channelLogo": "https://gh-proxy.com/https://raw.githubusercontent.com/fanmingming/live/main/tv/西藏卫视.png"
    },
    {
        "channelNum": 14,
        "channelName": "云南卫视",
        "channelUrl": "https://hwapi.yntv.net/62hdvf/41hse3.m3u8",
        "channelLogo": "https://gh-proxy.com/https://raw.githubusercontent.com/fanmingming/live/main/tv/云南卫视.png"
    },
    {
        "channelNum": 15,
        "channelName": "浙江卫视",
        "channelUrl": "https://zwebl02.cztv.com/live/channel011080P.m3u8?auth_key=1762409427-arotpvcxihq1gv739bswr5nja620ncky-0-c773762d7408156b622a3fccbd75e606",
        "channelLogo": "https://gh-proxy.com/https://raw.githubusercontent.com/fanmingming/live/main/tv/浙江卫视.png"
    }
]